dekpkglock-0.1.19.dist-info/METADATA
dekpkglock-0.1.19.dist-info/WHEEL
dekpkglock-0.1.19.dist-info/entry_points.txt
dekpkglock/__init__.py
dekpkglock/click/__entry__.py
dekpkglock/click/__init__.py
dekpkglock/core/__init__.py
dekpkglock/core/base/__init__.py
dekpkglock/core/pdm.py
dekpkglock/resources/pdm/dekspider/project/0.1.186/pdm.lock
dekpkglock/resources/pdm/dekspider/project/0.1.191/pdm.lock
dekpkglock/resources/pdm/dekspider/project/0.1.44/pdm.lock
dekpkglock/resources/pdm/dekspider/project/0.1.45/pdm.lock
dekpkglock/resources/pdm/dekspider/project/0.1.46/pdm.lock
dekpkglock/resources/pdm/dekspider/project/0.1.47/pdm.lock
dekpkglock/resources/pdm/dekspider/project/0.1.48/pdm.lock
dekpkglock/resources/pdm/dekspider/project/0.1.49/pdm.lock
dekpkglock/resources/pdm/dekspider/project/0.1.50/pdm.lock
dekpkglock/resources/pdm/dekspider/project/0.1.54/pdm.lock
dekpkglock/resources/pdm/dekspider/project/0.1.55/pdm.lock
dekpkglock/resources/pdm/dekspider/project/0.1.56/pdm.lock
dekpkglock/resources/pdm/dekspider/project/0.1.67/pdm.lock
dekpkglock/resources/pdm/djcreator/project/0.1.117/pdm.lock
dekpkglock/resources/pdm/djcreator/project/0.1.118/pdm.lock
dekpkglock/resources/pdm/djcreator/project/0.1.47/pdm.lock
dekpkglock/resources/pdm/djcreator/project/0.1.55/pdm.lock
dekpkglock/resources/pdm/djcreator/project/0.1.56/pdm.lock
dekpkglock/resources/pdm/djcreator/project/0.1.57/pdm.lock
dekpkglock/resources/pdm/djcreator/project/0.1.58/pdm.lock
dekpkglock/resources/pdm/djcreator/project/0.1.62/pdm.lock
dekpkglock/resources/pdm/djcreator/wrapper/0.1.117/pdm.lock
dekpkglock/resources/pdm/djcreator/wrapper/0.1.118/pdm.lock
dekpkglock/resources/pdm/djcreator/wrapper/0.1.47/pdm.lock
dekpkglock/resources/pdm/djcreator/wrapper/0.1.55/pdm.lock
dekpkglock/resources/pdm/djcreator/wrapper/0.1.56/pdm.lock
dekpkglock/resources/pdm/djcreator/wrapper/0.1.57/pdm.lock
dekpkglock/resources/pdm/djcreator/wrapper/0.1.58/pdm.lock
dekpkglock/resources/pdm/djcreator/wrapper/0.1.62/pdm.lock
dekpkglock-0.1.19.dist-info/RECORD
