Metadata-Version: 2.1
Name: dekpkglock
Version: 0.1.19
Author-Email: sanzenwin <sanzenwin@gmail.com>
License: MIT
Requires-Python: >=3.10
Requires-Dist: toml<=0.10.2
Requires-Dist: dektools<1.0.0
